example_package_asinedd/__init__.py
example_package_asinedd/main.py
example_package_asinedd-0.0.3.dist-info/METADATA
example_package_asinedd-0.0.3.dist-info/WHEEL
example_package_asinedd-0.0.3.dist-info/licenses/LICENSE
example_package_asinedd-0.0.3.dist-info/RECORD
