Metadata-Version: 2.1
Name: example_package_asinedd
Version: 0.0.3
Summary: A small example package
Project-URL: Homepage, https://github.com/asinedd/example-package-asinedd
Project-URL: Repository, https://github.com/asinedd/example-package-asinedd.git
Project-URL: Source, https://github.com/asinedd/example-package-asinedd
Author-email: asinedd <sind.bur.2@gmail.com>
License-File: LICENSE
Classifier: License :: OSI Approved :: MIT License
Classifier: Operating System :: OS Independent
Classifier: Programming Language :: Python :: 3
Requires-Python: >=3.8
Requires-Dist: requests
